{
	"burger": [
		{
			"name": "Burgers set",
			"price": "200",
			"img_src": "burger-1.png"
		},
		
		{
			"name": "Fish burger",
			"price": "170",
			"img_src": "burger-2.png"
		},
		
		{
			"name": "Cosmic burger",
			"price": "222",
			"img_src": "burger-3.png"
		},
		
		{
			"name": "Country burger",
			"price": "150",
			"img_src": "burger-4.png"
		},
		
		{
			"name": "Veggie burger",
			"price": "200",
			"img_src": "burger-5.png"
		},
		
		{
			"name": "Diet burger",
			"price": "220",
			"img_src": "burger-6.png"
		},
		
		{
			"name": "Cosmic Cola",
			"price": "40",
			"img_src": "burger-7.png"
		},
		
		{
			"name": "Ukrainian fries",
			"price": "90",
			"img_src": "burger-8.png"
		}
	],
	
	"kurcha": [
		{
			"name": "Yummy nuggets",
			"price": "220",
			"img_src": "chicken-1.jpg"
		},
		
		{
			"name": "Spicy wings",
			"price": "210",
			"img_src": "chicken-2.jpg"
		}
	],
	
	"sushi": [
		{
			"name": "Elegant sushi",
			"price": "150",
			"img_src": "sushi-1.png"
		},
		
		{
			"name": "Fantastic set",
			"price": "250",
			"img_src": "sushi-2.png"
		}
	],
	
	"borscht": [
		{
			"name": "Varyatskyi borscht",
			"price": "150",
			"img_src": "borscht-1.png"
		},
		
		{
			"name": "Nenashi varenyky",
			"price": "250",
			"img_src": "borscht-2.png"
		},
		
		{
			"name": "Dobri makarony",
			"price": "200",
			"img_src": "borscht-3.png"
		}
	]
}
